{
  "type": "farmersdelight:cooking",
  "container": {
    "item": "minecraft:bowl"
  },
  "cookingtime": 250,
  "experience": 1.5,
  "ingredients": [
    {
      "tag": "forge:crops/rice"
    },
    {
      "tag": "forge:raw_chicken"
    },
    {
      "tag": "forge:eggs"
    },
    {
      "tag": "forge:milk"
    },
    {
      "item": "minecraft:carrot"
    },
    {
      "tag": "forge:crops/cabbage"
    }
  ],
  "recipe_book_tab": "meals",
  "result": {
    "item": "largemeals:omurice_block"
  }
}